srppayouts/__init__.py
srppayouts/admin.py
srppayouts/app_settings.py
srppayouts/apps.py
srppayouts/auth_hooks.py
srppayouts/data_utils.py
srppayouts/models.py
srppayouts/tasks.py
srppayouts/urls.py
srppayouts/views.py
srppayouts/locale/.gitkeep
srppayouts/management/commands/srppayouts_load_data.py
srppayouts/management/commands/srppayouts_load_example.py
srppayouts/migrations/0001_initial.py
srppayouts/migrations/0002_reimbursement_ship_payout.py
srppayouts/migrations/0003_alter_general_options.py
srppayouts/migrations/__init__.py
srppayouts/static/dynamicsrp/.gitkeep
srppayouts/static/dynamicsrp/icons/12015.png
srppayouts/templates/srppayouts/base.html
srppayouts/templates/srppayouts/index.html
srppayouts/templatetags/icons_tags.py
srppayouts/tests/__init__.py
srppayouts/tests/test_example.py
aa_srppayouts-1.0.1.dist-info/LICENSE
aa_srppayouts-1.0.1.dist-info/WHEEL
aa_srppayouts-1.0.1.dist-info/METADATA
aa_srppayouts-1.0.1.dist-info/RECORD
