Metadata-Version: 2.1
Name: aa-srppayouts
Version: 1.0.1
Summary: Initialize the app
Author-email: Meowosaurus <info@bjsonnen.de>
Requires-Python: >=3.8
Classifier: Environment :: Web Environment
Classifier: Framework :: Django
Classifier: Framework :: Django :: 4.0
Classifier: Framework :: Django :: 4.2
Classifier: Intended Audience :: End Users/Desktop
Classifier: License :: OSI Approved :: MIT License
Classifier: Operating System :: OS Independent
Classifier: Programming Language :: Python
Classifier: Programming Language :: Python :: 3.8
Classifier: Programming Language :: Python :: 3.9
Classifier: Programming Language :: Python :: 3.10
Classifier: Programming Language :: Python :: 3.11
Classifier: Topic :: Internet :: WWW/HTTP
Classifier: Topic :: Internet :: WWW/HTTP :: Dynamic Content
Requires-Dist: allianceauth>=4.0
Project-URL: Changelog, https://gitlab.com/Meowosaurus/aa-srppayouts/-/blob/master/CHANGELOG.md
Project-URL: Homepage, https://gitlab.com/Meowosaurus/aa-srppayouts
Project-URL: Source, https://gitlab.com/Meowosaurus/aa-srppayouts
Project-URL: Tracker, https://gitlab.com/Meowosaurus/aa-srppayouts/-/issues
